{
  "project_info": {
    "project_number": "532440383611",
    "firebase_url": "https://newsnetwork-83160.firebaseio.com",
    "project_id": "newsnetwork-83160",
    "storage_bucket": "newsnetwork-83160.appspot.com"
  },
  "client": [
    {
      "client_info": {
        "mobilesdk_app_id": "1:532440383611:android:b46a78faeff7086afe22de",
        "android_client_info": {
          "package_name": "com.news.network"
        }
      },
      "oauth_client": [
        {
          "client_id": "532440383611-usggffhjs26iqdu0kql5ploah1gtfes4.apps.googleusercontent.com",
          "client_type": 1,
          "android_info": {
            "package_name": "com.news.network",
            "certificate_hash": "e4845d862786eb4352af95157580fa6f23e5f469"
          }
        },
        {
          "client_id": "532440383611-t1taj8elc09b3hki19aia4udcmij4use.apps.googleusercontent.com",
          "client_type": 3
        }
      ],
      "api_key": [
        {
          "current_key": "AIzaSyBmOAd9IH2O1MbvdZDSNKTTkB_E3255LEU"
        }
      ],
      "services": {
        "appinvite_service": {
          "other_platform_oauth_client": [
            {
              "client_id": "532440383611-t1taj8elc09b3hki19aia4udcmij4use.apps.googleusercontent.com",
              "client_type": 3
            }
          ]
        }
      }
    }
  ],
  "configuration_version": "1"
}